p_queue/__init__.py
p_queue/app.py
p_queue/utils.py
p_queue/worker.py
p_queuing-0.1.0.dist-info/licenses/LICENSE
p_queuing-0.1.0.dist-info/METADATA
p_queuing-0.1.0.dist-info/WHEEL
p_queuing-0.1.0.dist-info/entry_points.txt
p_queuing-0.1.0.dist-info/top_level.txt
p_queuing-0.1.0.dist-info/RECORD
