Metadata-Version: 2.4
Name: p_queuing
Version: 0.1.0
Summary: p_queuing Flask service & worker
Home-page: 
Author: Wares
Author-email: Wares <dr.wares007@gmail.com>
License: MIT
Requires-Python: >=3.8
License-File: LICENSE
Requires-Dist: flask
Requires-Dist: pika
Dynamic: author
Dynamic: license-file
Dynamic: requires-python
